Metadata-Version: 2.1
Name: sharkvalidator
Version: 0.1.12
Summary: Validate data delivery at the Swedish NODC
Home-page: https://github.com/sharksmhi/sharkvalidator
Author: SMHI - NODC
Author-email: shark@smhi.se
License: UNKNOWN
Platform: UNKNOWN
Classifier: Programming Language :: Python :: 3
Classifier: License :: OSI Approved :: MIT License
Classifier: Operating System :: OS Independent
Requires-Python: >=3.6
Requires-Dist: PyYAML
Requires-Dist: numpy
Requires-Dist: pandas
Requires-Dist: pyproj
Requires-Dist: requests
